<Map><Name>QuestaèUnaMappaSeria</Name><Width>1000</Width><Height>1000</Height><Number>5</Number><Objects><Headquarters><Headquarter>437,154</Headquarter><Headquarter>819,378</Headquarter><Headquarter>91,464</Headquarter><Headquarter>345,825</Headquarter><Headquarter>779,750</Headquarter></Headquarters><Fields><Field>76,156</Field><Field>628,269</Field><Field>276,489</Field><Field>234,625</Field><Field>543,739</Field><Field>863,577</Field></Fields><Caves><Cave>251,113</Cave><Cave>96,643</Cave><Cave>162,800</Cave><Cave>826,166</Cave><Cave>658,828</Cave></Caves><Woods><Wood>301,328</Wood><Wood>500,327</Wood><Wood>646,130</Wood><Wood>515,500</Wood><Wood>394,673</Wood><Wood>688,516</Wood></Woods></Objects></Map>